_miniaudio.abi3.so
miniaudio.py
miniaudio-1.61.dist-info/WHEEL
miniaudio-1.61.dist-info/LICENSE
miniaudio-1.61.dist-info/top_level.txt
miniaudio-1.61.dist-info/RECORD
miniaudio-1.61.dist-info/METADATA
