Metadata-Version: 2.1
Name: miniaudio
Version: 1.61
Summary: python bindings for the miniaudio library and its decoders (mp3, flac, ogg vorbis, wav)
Home-page: https://github.com/irmen/pyminiaudio
Author: Irmen de Jong
Author-email: irmen@razorvine.net
License: MIT
Keywords: sound,audio,playback,recording,conversion,decoding
Classifier: Development Status :: 5 - Production/Stable
Classifier: License :: OSI Approved :: MIT License
Classifier: Programming Language :: C
Classifier: Programming Language :: Python
Classifier: Programming Language :: Python :: 3
Classifier: Topic :: Multimedia :: Sound/Audio
Classifier: Topic :: Multimedia :: Sound/Audio :: Conversion
Classifier: Topic :: Multimedia :: Sound/Audio :: Capture/Recording
Classifier: Topic :: Multimedia :: Sound/Audio :: Players
License-File: LICENSE
